OSMAlchemy-0.1.3.dist-info/DESCRIPTION.rst
OSMAlchemy-0.1.3.dist-info/METADATA
OSMAlchemy-0.1.3.dist-info/RECORD
OSMAlchemy-0.1.3.dist-info/WHEEL
OSMAlchemy-0.1.3.dist-info/metadata.json
OSMAlchemy-0.1.3.dist-info/top_level.txt
OSMAlchemy-0.1.3.dist-info/zip-safe
osmalchemy/__init__.py
osmalchemy/model.py
osmalchemy/osmalchemy.py
osmalchemy/triggers.py
osmalchemy/util/__init__.py
osmalchemy/util/db.py
osmalchemy/util/online.py
osmalchemy/util/patch.py
