Metadata-Version: 2.0
Name: OSMAlchemy
Version: 0.1.3
Summary: OpenStreetMap to SQLAlchemy bridge
Home-page: https://github.com/Veripeditus/OSMAlchemy
Author: Dominik George, Eike Tim Jesinghaus
Author-email: osmalchemy@veripeditus.org
License: UNKNOWN
Keywords: osm,openstreetmap,proxy,caching,orm
Platform: UNKNOWN
Classifier: Development Status :: 3 - Alpha
Classifier: Environment :: Plugins
Classifier: Intended Audience :: Developers
Classifier: License :: OSI Approved :: MIT License
Classifier: Programming Language :: Python :: 3 :: Only
Classifier: Topic :: Database
Classifier: Topic :: Scientific/Engineering :: GIS
Classifier: Topic :: Software Development :: Libraries :: Python Modules
Requires-Dist: SQLAlchemy (>=1.0.0)
Requires-Dist: overpass
Requires-Dist: python-dateutil
Provides-Extra: Flask
Requires-Dist: Flask (>=0.10); extra == 'Flask'
Requires-Dist: Flask-SQLAlchemy; extra == 'Flask'
